cardinal/__init__.py
cardinal/collector/__init__.py
cardinal/collector/base_collector.py
cardinal/collector/chat_collector.py
cardinal/collector/schema.py
cardinal/common/__init__.py
cardinal/common/message.py
cardinal/common/template.py
cardinal/graph/__init__.py
cardinal/graph/auto.py
cardinal/graph/config.py
cardinal/graph/neo4j.py
cardinal/graph/schema.py
cardinal/logging/__init__.py
cardinal/logging/logger.py
cardinal/model/__init__.py
cardinal/model/chat_openai.py
cardinal/model/config.py
cardinal/model/embed_openai.py
cardinal/model/reranker.py
cardinal/model/token_counter.py
cardinal/retriever/__init__.py
cardinal/retriever/dense_retriever.py
cardinal/retriever/hybrid_retriever.py
cardinal/retriever/multi_retriever.py
cardinal/retriever/schema.py
cardinal/retriever/sparse_retriever.py
cardinal/splitter/__init__.py
cardinal/splitter/config.py
cardinal/splitter/text_splitter.py
cardinal/storage/__init__.py
cardinal/storage/auto.py
cardinal/storage/config.py
cardinal/storage/elasticsearch.py
cardinal/storage/redis.py
cardinal/storage/schema.py
cardinal/utils/__init__.py
cardinal/utils/import_utils.py
cardinal/vectorstore/__init__.py
cardinal/vectorstore/auto.py
cardinal/vectorstore/chroma.py
cardinal/vectorstore/config.py
cardinal/vectorstore/elasticsearch.py
cardinal/vectorstore/milvus.py
cardinal/vectorstore/schema.py
pycardinal-0.5.1.dist-info/licenses/LICENSE
pycardinal-0.5.1.dist-info/METADATA
pycardinal-0.5.1.dist-info/WHEEL
pycardinal-0.5.1.dist-info/top_level.txt
pycardinal-0.5.1.dist-info/RECORD
